README.md
setup.cfg
setup.py
hummingbird/__init__.py
hummingbird/setting.py
hummingbird/downloader/__init__.py
hummingbird/downloader/async.py
hummingbird/downloader/base.py
hummingbird/filter/__init__.py
hummingbird/pipeline/__init__.py
hummingbird/pipeline/base.py
hummingbird/scheduler/__init__.py
hummingbird/scheduler/base.py
hummingbird/scheduler/queue.py
hummingbird/scheduler/redis.py
hummingbird/spider/__init__.py
hummingbird/spider/base.py
hummingbird/spider/crawl.py
hummingbird/spider/simple.py
hummingbird/utils/__init__.py
hummingbird/utils/call.py
magician.egg-info/PKG-INFO
magician.egg-info/SOURCES.txt
magician.egg-info/dependency_links.txt
magician.egg-info/requires.txt
magician.egg-info/top_level.txt